{
  "filename": "a_acorn_squash_36px.png",
  "status": "success",
  "description": {
    "detailed_description": "This font, with its flowing curves and expressive strokes, embodies a playful yet sophisticated spirit. The calligraphic origins are evident in the fluid transitions between strokes, particularly in the lowercase letters. The generous x-height and open counters ensure excellent legibility, even at smaller sizes. The font's overall character is one of warmth and approachability, with a touch of whimsy. It evokes a sense of handwritten charm, reminiscent of vintage signage or personalized stationery. This makes it ideal for branding projects that seek a friendly and inviting aesthetic, particularly in the realm of lifestyle, food, or creative industries. The font's versatility extends to digital applications, where it can add a touch of personality to websites, social media graphics, and even mobile interfaces.",
    "technical_characteristics": [
      "Calligraphic construction",
      "Fluid stroke transitions",
      "Generous x-height",
      "Open counters",
      "Varying stroke weights",
      "Cursive style",
      "Dynamic letterforms"
    ],
    "personality_traits": [
      "Playful yet sophisticated",
      "Warm and approachable",
      "Whimsical and charming",
      "Handwritten aesthetic",
      "Friendly and inviting",
      "Expressive and dynamic",
      "Versatile and adaptable"
    ],
    "practical_contexts": [
      "Branding for lifestyle, food, and creative industries",
      "Handwritten-style signage and stationery",
      "Digital applications like websites and social media",
      "Headlines and titles for print and digital media",
      "Short text blocks for readability"
    ],
    "cultural_intuition": [
      "Evokes vintage charm and nostalgia",
      "Suggests a sense of handcrafted quality",
      "Reflects a contemporary appreciation for handwritten aesthetics",
      "Connects to a culture of authenticity and personality",
      "Appeals to a wide audience seeking warmth and approachability"
    ],
    "search_keywords": [
      "Calligraphic",
      "Cursive",
      "Script",
      "Handwritten",
      "Playful",
      "Sophisticated",
      "Warm",
      "Approachable",
      "Whimsical",
      "Charming",
      "Vintage",
      "Nostalgia",
      "Branding",
      "Lifestyle",
      "Food",
      "Creative",
      "Digital",
      "Website",
      "Social media",
      "Headlines",
      "Titles",
      "Short text",
      "Readability"
    ]
  }
}