{
  "filename": "bad_quality_36px.png",
  "status": "success",
  "description": {
    "detailed_description": "This font, with its playful, almost cartoonish aesthetic, is a prime example of a display typeface designed for impact. The letterforms are characterized by a distinct, almost eroded, quality, with rounded corners and uneven edges that give the impression of hand-drawn lettering. This deliberate imperfection adds a sense of whimsy and informality, making it ideal for grabbing attention in headlines or branding elements. The font's generous x-height and open counters ensure legibility even at larger sizes, while the exaggerated curves and playful swashes contribute to its overall sense of fun. While the font's technical execution is intentionally rough, it's precisely this imperfection that contributes to its unique charm. It evokes a sense of nostalgia, reminiscent of vintage signage or hand-drawn posters, while simultaneously feeling fresh and contemporary. This font is best suited for short bursts of text, where its playful personality can shine. It's perfect for adding a touch of whimsy to branding, packaging, or digital interfaces, particularly in contexts where a sense of fun and approachability is desired.",
    "technical_characteristics": [
      "Rounded corners",
      "Uneven edges",
      "Exaggerated curves",
      "Open counters",
      "Generous x-height",
      "Playful swashes",
      "Intentional imperfection"
    ],
    "personality_traits": [
      "Playful",
      "Whimsical",
      "Informal",
      "Nostalgic",
      "Fun",
      "Approachable",
      "Bold",
      "Eye-catching",
      "Hand-drawn",
      "Vintage"
    ],
    "practical_contexts": [
      "Headlines",
      "Branding elements",
      "Packaging design",
      "Digital interfaces",
      "Short bursts of text"
    ],
    "cultural_intuition": [
      "Evokes vintage signage",
      "Reminiscent of hand-drawn posters",
      "Suggests a sense of fun and approachability",
      "Reflects a contemporary trend towards playful typography",
      "Captures a sense of nostalgia"
    ],
    "search_keywords": [
      "Display font",
      "Playful font",
      "Whimsical font",
      "Hand-drawn font",
      "Cartoon font",
      "Vintage font",
      "Nostalgic font",
      "Bold font",
      "Eye-catching font",
      "Informal font",
      "Fun font",
      "Approachable font",
      "Branding font",
      "Headline font",
      "Packaging font",
      "Digital font",
      "Eroded font",
      "Rounded corners",
      "Open counters",
      "Generous x-height",
      "Playful swashes",
      "Imperfect font"
    ]
  }
}