{
  "filename": "chicken_scratch_aoe_36px.png",
  "status": "success",
  "description": {
    "detailed_description": "Chicken Scratch AOE is a bold, expressive script font that captures the energy of hand-drawn lettering. Its irregular, gestural strokes and uneven letterforms create a sense of immediacy and authenticity. The font's high x-height and open counters ensure strong legibility, even at smaller sizes. The exaggerated ascenders and descenders add to its dynamic character, while the slightly rounded terminals soften its impact. This combination of boldness and approachability makes it suitable for a wide range of applications, from eye-catching headlines to casual social media posts. The font's raw, unrefined aesthetic evokes a sense of rebellion and individuality, reminiscent of punk rock aesthetics and DIY culture. It's a font that speaks to those who value authenticity and self-expression, and its playful energy makes it perfect for projects that demand a touch of irreverence.",
    "technical_characteristics": [
      "Irregular, gestural strokes",
      "Uneven letterforms",
      "High x-height",
      "Open counters",
      "Exaggerated ascenders and descenders",
      "Slightly rounded terminals"
    ],
    "personality_traits": [
      "Bold and expressive",
      "Energetic and dynamic",
      "Raw and unrefined",
      "Playful and irreverent",
      "Authentic and individualistic",
      "Rebellious and edgy",
      "Approachable and friendly"
    ],
    "practical_contexts": [
      "Headlines and titles",
      "Social media graphics",
      "Posters and flyers",
      "Branding for creative businesses",
      "Casual and informal designs"
    ],
    "cultural_intuition": [
      "Punk rock aesthetics",
      "DIY culture",
      "Street art and graffiti",
      "Rebellious youth culture",
      "Authenticity and self-expression"
    ],
    "search_keywords": [
      "script font",
      "handwritten font",
      "bold font",
      "expressive font",
      "casual font",
      "punk font",
      "graffiti font",
      "street art font",
      "rebellious font",
      "individualistic font",
      "authentic font",
      "high x-height",
      "open counters",
      "irregular strokes",
      "uneven letterforms",
      "rounded terminals",
      "headlines",
      "social media",
      "posters",
      "flyers",
      "branding",
      "creative businesses",
      "casual designs"
    ]
  }
}