{
  "filename": "children_bats_36px.png",
  "status": "success",
  "description": {
    "detailed_description": "This font is a playful and whimsical interpretation of a classic cartoon style. Each letterform is a unique illustration of a baby engaged in various activities, from playing with toys to riding in a stroller. The font's construction is based on simple, rounded shapes, creating a sense of childlike innocence and charm. The exaggerated features, such as large eyes and chubby cheeks, further enhance the playful nature of the design. While the font's technical execution is straightforward, its distinctive character lies in its ability to evoke a sense of nostalgia and lightheartedness. The font's intended application is primarily for children's books, branding for baby products, or playful digital designs. Its limited character set and whimsical nature make it less suitable for formal or professional contexts. However, its ability to capture a sense of joy and wonder makes it ideal for projects that aim to engage a younger audience.",
    "technical_characteristics": [
      "Cartoon-inspired construction",
      "Rounded letterforms",
      "Exaggerated features",
      "Limited character set",
      "Simple linework",
      "Consistent stroke weight",
      "Hand-drawn aesthetic"
    ],
    "personality_traits": [
      "Playful",
      "Whimsical",
      "Nostalgic",
      "Charming",
      "Childlike",
      "Innocent",
      "Lighthearted"
    ],
    "practical_contexts": [
      "Children's books",
      "Baby product branding",
      "Playful digital designs",
      "Greeting cards",
      "Educational materials"
    ],
    "cultural_intuition": [
      "Evokes childhood memories",
      "Suggests a sense of fun and joy",
      "Reflects a playful and optimistic outlook",
      "Connects to a sense of innocence and wonder",
      "Appeals to a wide range of ages"
    ],
    "search_keywords": [
      "Cartoon font",
      "Baby font",
      "Whimsical font",
      "Playful font",
      "Nostalgic font",
      "Children's font",
      "Hand-drawn font",
      "Illustrated font",
      "Fun font",
      "Joyful font",
      "Cute font",
      "Charming font",
      "Limited character set",
      "Simple font",
      "Rounded font",
      "Graphic font",
      "Display font",
      "Branding font",
      "Digital font",
      "Web font"
    ]
  }
}