{
  "filename": "disolve_36px.png",
  "status": "success",
  "description": {
    "detailed_description": "This font, built upon a geometric framework, exhibits a striking simplicity that borders on minimalism. Each letterform is constructed from a series of straight lines and sharp angles, creating a sense of starkness and precision. The consistent stroke weight and lack of embellishment contribute to its clean, uncluttered aesthetic. While the overall impression is one of rigidity and order, subtle variations in the angles and curves within each letter, particularly in the lowercase, introduce a touch of humanism, preventing the font from feeling overly cold or robotic. This balance between geometric structure and subtle organic elements makes it suitable for a wide range of applications, from bold headlines and technical documentation to contemporary branding and digital interfaces. Its clean lines and strong legibility ensure readability even at small sizes, making it ideal for web and mobile use. The font's starkness and geometric nature evoke a sense of modernity and technological advancement, suggesting a connection to the digital age and the world of data and information. It carries a subtle air of mystery and intrigue, hinting at hidden complexities beneath its seemingly simple exterior.",
    "technical_characteristics": [
      "Geometric construction",
      "Consistent stroke weight",
      "Sharp angles and straight lines",
      "Open counters",
      "High x-height",
      "Minimalist design",
      "Subtle variations in angles and curves"
    ],
    "personality_traits": [
      "Stark and precise",
      "Clean and uncluttered",
      "Modern and technological",
      "Bold and confident",
      "Intriguing and mysterious",
      "Subtly humanistic",
      "Readable and versatile"
    ],
    "practical_contexts": [
      "Headlines and titles",
      "Technical documentation",
      "Branding and logos",
      "Digital interfaces",
      "Web and mobile design"
    ],
    "cultural_intuition": [
      "Evokes a sense of modernity and technological advancement",
      "Suggests a connection to the digital age and the world of data",
      "Carries a subtle air of mystery and intrigue",
      "Hinting at hidden complexities",
      "Reflects a contemporary design aesthetic"
    ],
    "search_keywords": [
      "Geometric sans-serif",
      "Minimalist font",
      "Modern typeface",
      "Digital font",
      "Clean and bold",
      "High x-height",
      "Sharp angles",
      "Open counters",
      "Technical documentation",
      "Branding",
      "Web design",
      "Mobile design",
      "Intriguing",
      "Mysterious",
      "Contemporary"
    ]
  }
}