{
  "filename": "dubbem_36px.png",
  "status": "success",
  "description": {
    "detailed_description": "Dubber is a playful display font that embraces a hand-drawn aesthetic. Its irregular letterforms, with their rounded corners and exaggerated curves, evoke a sense of childlike energy and spontaneity. The font's construction is loose and organic, with each letter seemingly drawn with a single, confident stroke. This casual approach creates a sense of immediacy and informality, making it ideal for projects that require a friendly and approachable tone. The font's generous x-height and open counters ensure good legibility, even at smaller sizes, while its bold weight adds visual impact. Dubber's playful nature makes it perfect for branding projects targeting younger audiences, as well as for creating eye-catching headlines, logos, and packaging designs. Its hand-drawn quality evokes a sense of authenticity and warmth, making it suitable for projects that aim to connect with audiences on an emotional level.",
    "technical_characteristics": [
      "Hand-drawn aesthetic",
      "Irregular letterforms",
      "Rounded corners",
      "Exaggerated curves",
      "Generous x-height",
      "Open counters",
      "Bold weight"
    ],
    "personality_traits": [
      "Playful",
      "Spontaneous",
      "Friendly",
      "Approachable",
      "Casual",
      "Energetic",
      "Bold"
    ],
    "practical_contexts": [
      "Branding for younger audiences",
      "Headlines",
      "Logos",
      "Packaging design",
      "Social media graphics"
    ],
    "cultural_intuition": [
      "Evokes a sense of childhood nostalgia",
      "Suggests creativity and imagination",
      "Reflects a contemporary trend towards hand-drawn aesthetics",
      "Connects with a desire for authenticity and warmth"
    ],
    "search_keywords": [
      "Hand-drawn",
      "Playful",
      "Display font",
      "Casual",
      "Bold",
      "Irregular",
      "Rounded",
      "Exaggerated",
      "Generous x-height",
      "Open counters",
      "Branding",
      "Headlines",
      "Logos",
      "Packaging",
      "Social media",
      "Nostalgia",
      "Creativity",
      "Authenticity",
      "Warmth"
    ]
  }
}