{
  "filename": "enochian_36px.png",
  "status": "success",
  "description": {
    "detailed_description": "This font is a captivating blend of medieval script and modern graphic design. Its organic, flowing forms are reminiscent of calligraphic writing, with sharp angles and dramatic curves that create a sense of movement and energy. The letterforms are highly stylized, with each character possessing a unique and distinctive shape. The font's bold strokes and generous x-height contribute to its strong visual presence, making it ideal for headlines and display applications. While its historical roots are evident, the font's clean lines and contemporary execution give it a modern edge, making it suitable for a range of projects from branding and packaging to digital interfaces and editorial design. The font's bold and expressive nature evokes a sense of power and authority, while its playful and whimsical elements add a touch of personality and intrigue. It's a font that demands attention and invites exploration, making it perfect for projects that seek to stand out and make a statement.",
    "technical_characteristics": [
      "Organic, flowing forms",
      "Sharp angles and dramatic curves",
      "Highly stylized letterforms",
      "Bold strokes",
      "Generous x-height",
      "Open counters",
      "Consistent stroke weight"
    ],
    "personality_traits": [
      "Bold and expressive",
      "Playful and whimsical",
      "Energetic and dynamic",
      "Authoritative and powerful",
      "Intriguing and captivating"
    ],
    "practical_contexts": [
      "Headlines and display typography",
      "Branding and packaging design",
      "Digital interfaces and web design",
      "Editorial design and magazine layouts",
      "Posters and signage"
    ],
    "cultural_intuition": [
      "Medieval script and calligraphy",
      "Modern graphic design and digital culture",
      "A sense of power and authority",
      "A touch of whimsy and playfulness",
      "A font that demands attention and invites exploration"
    ],
    "search_keywords": [
      "Blackletter",
      "Script",
      "Calligraphy",
      "Bold",
      "Expressive",
      "Playful",
      "Whimsical",
      "Energetic",
      "Dynamic",
      "Modern",
      "Contemporary",
      "Graphic design",
      "Digital",
      "Branding",
      "Packaging",
      "Editorial",
      "Display",
      "Headline",
      "Poster",
      "Signage"
    ]
  }
}