{
  "filename": "eureka_36px.png",
  "status": "success",
  "description": {
    "detailed_description": "Eureka is a display typeface that blends classic calligraphic flourishes with a contemporary, almost playful, sensibility. Its construction is based on a combination of geometric and organic forms, resulting in a unique visual language. The letters are characterized by their bold strokes, open counters, and distinctive terminals, often ending in elegant swashes or serifs. This combination of elements creates a font that is both eye-catching and legible, making it suitable for a variety of applications. The overall character of Eureka is one of confident charm, suggesting a sense of whimsy and sophistication. It evokes a sense of vintage elegance, reminiscent of early 20th-century lettering styles, but with a modern twist. This makes it particularly well-suited for branding projects, logos, and headlines, where it can add a touch of personality and visual interest. However, its intricate details and bold strokes may limit its effectiveness in smaller sizes or for extended body text.",
    "technical_characteristics": [
      "Bold strokes",
      "Open counters",
      "Distinctive terminals",
      "Geometric and organic construction",
      "High x-height",
      "Variable stroke widths",
      "Swash variations"
    ],
    "personality_traits": [
      "Confidently charming",
      "Playfully elegant",
      "Visually striking",
      "Sophisticatedly whimsical",
      "Vintage-inspired",
      "Modernly classic",
      "Boldly expressive"
    ],
    "practical_contexts": [
      "Branding and logos",
      "Headlines and titles",
      "Posters and signage",
      "Display typography",
      "Limited body text"
    ],
    "cultural_intuition": [
      "Evokes early 20th-century lettering styles",
      "Suggests a sense of vintage elegance",
      "Reflects a contemporary appreciation for handcrafted design",
      "Connects to a playful and sophisticated aesthetic",
      "Appeals to a modern audience seeking unique visual identity"
    ],
    "search_keywords": [
      "Display typeface",
      "Calligraphic",
      "Geometric",
      "Organic",
      "Bold strokes",
      "Open counters",
      "Distinctive terminals",
      "Swash variations",
      "Vintage",
      "Elegant",
      "Playful",
      "Sophisticated",
      "Branding",
      "Logos",
      "Headlines",
      "Posters",
      "Signage"
    ]
  }
}