{
  "filename": "first_aid_36px.png",
  "status": "success",
  "description": {
    "detailed_description": "This font, constructed from a series of overlapping squares, presents a unique and playful take on typography. The individual squares, resembling adhesive bandages, create a distinct visual texture, adding a sense of depth and dimensionality to the letterforms. The irregular arrangement of these squares within each letter results in a slightly uneven, almost hand-drawn aesthetic, contrasting with the geometric foundation. This combination of geometric structure and organic irregularity gives the font a charming and approachable personality, making it suitable for projects that require a touch of whimsy and a sense of friendly informality. The font's bold, graphic nature makes it ideal for headlines, logos, and other display applications, particularly in contexts where a playful and approachable tone is desired. Its unique visual language evokes a sense of childhood nostalgia, reminiscent of playful band-aid designs and DIY crafts, while also suggesting a contemporary, digital-native aesthetic.",
    "technical_characteristics": [
      "constructed from overlapping squares",
      "irregular arrangement of squares within letters",
      "uneven, hand-drawn aesthetic",
      "bold, graphic forms",
      "pronounced x-height",
      "open counters",
      "distinctive, textured surface"
    ],
    "personality_traits": [
      "playful and approachable",
      "whimsical and charming",
      "bold and graphic",
      "informal and friendly",
      "nostalgic and playful",
      "contemporary and digital-native"
    ],
    "practical_contexts": [
      "headlines and titles",
      "logos and branding",
      "display typography",
      "packaging and product design",
      "children's books and educational materials"
    ],
    "cultural_intuition": [
      "evokes childhood nostalgia",
      "suggests DIY crafts and playful designs",
      "reminiscent of band-aid imagery",
      "reflects a contemporary, digital-native aesthetic",
      "captures a sense of friendly informality"
    ],
    "search_keywords": [
      "band-aid font",
      "square font",
      "geometric font",
      "playful font",
      "whimsical font",
      "informal font",
      "nostalgic font",
      "digital font",
      "display font",
      "headline font",
      "logo font",
      "packaging font",
      "children's font",
      "educational font",
      "graphic font",
      "textured font",
      "overlapping squares",
      "irregular arrangement",
      "hand-drawn aesthetic",
      "bold forms",
      "open counters",
      "high x-height"
    ]
  }
}