{
  "filename": "i_do_not_trust_you_36px.png",
  "status": "success",
  "description": {
    "detailed_description": "This font exhibits a playful, almost childlike energy, achieved through a combination of rounded forms, exaggerated proportions, and a distinct hand-drawn aesthetic. The letterforms are characterized by their uneven strokes, inconsistent widths, and a general lack of strict geometric precision. This informality is further emphasized by the inclusion of playful flourishes, such as the extended tails on the 'f' and 'g' and the whimsical 'Q' with its exaggerated loop. While the font lacks the formal structure of traditional typefaces, it compensates with a charming, approachable personality. Its casual nature makes it ideal for informal projects, particularly those targeting younger audiences or conveying a sense of fun and lightheartedness. The font's hand-drawn quality evokes a sense of authenticity and personal expression, making it suitable for projects that emphasize individuality and creativity. However, its lack of consistency and legibility at smaller sizes might limit its use in large blocks of text or formal settings.",
    "technical_characteristics": [
      "Hand-drawn aesthetic",
      "Rounded forms",
      "Uneven strokes",
      "Inconsistent letter widths",
      "Exaggerated proportions",
      "Playful flourishes",
      "Informal construction"
    ],
    "personality_traits": [
      "Playful",
      "Whimsical",
      "Charming",
      "Approachable",
      "Casual",
      "Hand-drawn",
      "Informal"
    ],
    "practical_contexts": [
      "Informal branding",
      "Children's books",
      "Social media graphics",
      "Hand-lettered signage",
      "Short text elements"
    ],
    "cultural_intuition": [
      "Evokes a sense of childhood nostalgia",
      "Suggests creativity and individuality",
      "Reflects a contemporary trend towards hand-drawn aesthetics",
      "Conveys a sense of fun and lightheartedness"
    ],
    "search_keywords": [
      "Hand-drawn",
      "Playful",
      "Informal",
      "Whimsical",
      "Rounded",
      "Casual",
      "Childlike",
      "Nostalgic",
      "Creative",
      "Authentic",
      "Branding",
      "Social media",
      "Children's book",
      "Signage",
      "Short text"
    ]
  }
}