{
  "filename": "innsmouth_plain_36px.png",
  "status": "success",
  "description": {
    "detailed_description": "Innsmouth Plain embodies a playful yet refined aesthetic, drawing inspiration from both traditional script fonts and contemporary digital design. Its flowing curves and delicate flourishes evoke a sense of handwritten elegance, while its consistent stroke weights and clear letterforms ensure readability. The font's rounded terminals and open counters contribute to its approachable and friendly character, making it suitable for a wide range of applications. While its whimsical nature suggests a lighthearted tone, the font's overall structure maintains a sense of sophistication, making it appropriate for both playful and more formal contexts. The font's digital origins are evident in its smooth curves and consistent linework, suggesting a modern and adaptable personality.",
    "technical_characteristics": [
      "Cursive construction",
      "Variable stroke weights",
      "Rounded terminals",
      "Open counters",
      "Consistent x-height"
    ],
    "personality_traits": [
      "Playfully elegant",
      "Delicately whimsical",
      "Approachable and friendly",
      "Sophisticated yet casual",
      "Digitally refined"
    ],
    "practical_contexts": [
      "Branding for creative businesses",
      "Website headers and titles",
      "Social media graphics",
      "Invitations and stationery",
      "Children's books and illustrations"
    ],
    "cultural_intuition": [
      "Evokes a sense of handwritten charm",
      "Suggests a playful and optimistic spirit",
      "Reflects a contemporary appreciation for handcrafted aesthetics",
      "Connects to a digital-native design sensibility",
      "Appeals to a wide audience seeking a balance of elegance and approachability"
    ],
    "search_keywords": [
      "Cursive font",
      "Script font",
      "Playful font",
      "Elegant font",
      "Handwritten font",
      "Digital font",
      "Modern font",
      "Branding font",
      "Website font",
      "Social media font",
      "Invitation font",
      "Children's font",
      "Whimsical font",
      "Sophisticated font",
      "Approachable font"
    ]
  }
}