{
  "filename": "kingsbridge_36px.png",
  "status": "success",
  "description": {
    "detailed_description": "Kingsbridge is a contemporary sans-serif typeface that blends a classic geometric foundation with subtle humanist details. Its construction is rooted in precise geometric shapes, evident in the consistent width of strokes and the clean, unornamented terminals. However, the font avoids a purely rigid aesthetic by introducing slight curves and subtle variations in letterforms, particularly in the lowercase. This balance creates a typeface that is both modern and approachable, with a strong sense of clarity and legibility. The high x-height and open counters ensure readability even at small sizes, making it suitable for digital interfaces and web design. The overall character of Kingsbridge is confident and professional, yet it retains a friendly and inviting quality. Its clean lines and balanced proportions evoke a sense of order and efficiency, while the subtle humanist touches add a touch of warmth and approachability. This makes it a versatile choice for a wide range of applications, from corporate branding to editorial design. The font's contemporary relevance lies in its ability to bridge the gap between traditional typographic principles and the demands of modern digital design. It offers a clean and modern aesthetic without sacrificing readability or personality, making it a strong choice for projects that require a balance of sophistication and accessibility.",
    "technical_characteristics": [
      "Geometric construction",
      "Consistent stroke width",
      "High x-height",
      "Open counters",
      "Subtly rounded terminals",
      "Balanced proportions",
      "Clean, unornamented letterforms"
    ],
    "personality_traits": [
      "Confidently geometric",
      "Subtly humanist",
      "Clearly legible",
      "Professionally refined",
      "Approachable and friendly",
      "Modern and versatile",
      "Digitally adaptable"
    ],
    "practical_contexts": [
      "Web design and digital interfaces",
      "Corporate branding and identity",
      "Editorial design and publications",
      "Marketing materials and advertising",
      "User interface design and mobile applications"
    ],
    "cultural_intuition": [
      "Evokes a sense of modern efficiency",
      "Suggests a clean and professional aesthetic",
      "Reflects a contemporary design sensibility",
      "Connects to a culture of digital communication",
      "Embraces a balance of tradition and innovation"
    ],
    "search_keywords": [
      "Sans-serif",
      "Geometric",
      "Humanist",
      "Modern",
      "Contemporary",
      "Legible",
      "Professional",
      "Versatile",
      "Digital",
      "Web",
      "Branding",
      "Editorial",
      "Marketing",
      "Interface",
      "Clean",
      "Efficient",
      "Approachable",
      "Friendly",
      "High x-height",
      "Open counters",
      "Rounded terminals",
      "Balanced proportions",
      "Consistent stroke width"
    ]
  }
}