{
  "filename": "kogok_36px.png",
  "status": "success",
  "description": {
    "detailed_description": "This font, with its bold, confident strokes and sharp angles, evokes a sense of power and authority. The geometric construction, evident in the consistent proportions and clean lines, lends a sense of order and precision. The high x-height and open counters ensure strong legibility, even at smaller sizes, making it suitable for both print and digital applications. The slightly condensed letterforms add a touch of dynamism, while the sharp terminals and strong serifs contribute to a sense of formality. The overall character is both modern and classic, drawing inspiration from Art Deco and Bauhaus aesthetics while maintaining a timeless appeal. Its bold presence makes it ideal for headlines, branding, and editorial design, particularly for projects that require a strong visual impact and a sense of sophistication.",
    "technical_characteristics": [
      "Geometric construction",
      "High x-height",
      "Open counters",
      "Sharp terminals",
      "Strong serifs",
      "Slightly condensed letterforms",
      "Bold weight"
    ],
    "personality_traits": [
      "Confidently geometric",
      "Visually striking",
      "Formally elegant",
      "Modern yet timeless",
      "Powerful and authoritative",
      "Dynamic and energetic",
      "Sophisticated and refined"
    ],
    "practical_contexts": [
      "Headlines and titles",
      "Branding and logos",
      "Editorial design",
      "Posters and signage",
      "Digital interfaces"
    ],
    "cultural_intuition": [
      "Evokes Art Deco and Bauhaus aesthetics",
      "Suggests a sense of power and authority",
      "Reflects a modern, confident sensibility",
      "Connects to a sense of order and precision",
      "Appeals to a sophisticated audience"
    ],
    "search_keywords": [
      "Geometric sans-serif",
      "Bold font",
      "High x-height",
      "Sharp terminals",
      "Open counters",
      "Condensed font",
      "Art Deco",
      "Bauhaus",
      "Modern font",
      "Classic font",
      "Powerful font",
      "Authoritative font",
      "Sophisticated font",
      "Headlines",
      "Branding",
      "Editorial design",
      "Digital design"
    ]
  }
}