{
  "filename": "lightning_bolts_36px.png",
  "status": "success",
  "description": {
    "detailed_description": "This font is a captivating exploration of organic forms, drawing inspiration from the intricate patterns of natural elements like branches and roots. Each letter is a unique, hand-drawn stroke, creating a sense of raw energy and unpredictable beauty. The irregular, branching lines and sharp angles give the font a distinct, almost chaotic character, yet it maintains a surprising level of legibility due to the clear contrast between thick and thin strokes. The font's organic nature lends itself to applications where a sense of naturalness and authenticity is desired, such as branding for eco-conscious businesses, artistic projects, or even graphic design elements that evoke a sense of wilderness or untamed growth. The font's raw, unrefined aesthetic suggests a connection to nature and a rejection of rigid, artificial structures, making it a powerful tool for conveying a sense of authenticity and individuality.",
    "technical_characteristics": [
      "Hand-drawn style",
      "Irregular, branching strokes",
      "Sharp angles and curves",
      "High contrast between thick and thin strokes",
      "Variable letterforms",
      "Organic, asymmetrical construction",
      "Limited character set"
    ],
    "personality_traits": [
      "Raw and energetic",
      "Unpredictable and dynamic",
      "Natural and organic",
      "Authentic and individualistic",
      "Chaotic yet legible",
      "Visually striking and memorable",
      "Emotive and expressive"
    ],
    "practical_contexts": [
      "Branding for eco-conscious businesses",
      "Artistic projects and illustrations",
      "Graphic design elements that evoke nature",
      "Headlines and titles",
      "Short text blocks"
    ],
    "cultural_intuition": [
      "Evokes a sense of wilderness and untamed growth",
      "Connects to the natural world and organic forms",
      "Suggests a rejection of artificiality and conformity",
      "Reflects a contemporary appreciation for authenticity and individuality",
      "Can be interpreted as both beautiful and unsettling"
    ],
    "search_keywords": [
      "Hand-drawn",
      "Organic",
      "Natural",
      "Branch",
      "Root",
      "Chaotic",
      "Unpredictable",
      "Energetic",
      "Authentic",
      "Individualistic",
      "Wilderness",
      "Untamed",
      "Nature",
      "Art",
      "Graphic design",
      "Branding",
      "Eco-conscious",
      "Headlines",
      "Titles",
      "Short text",
      "Emotive",
      "Expressive",
      "Beautiful",
      "Unsettling"
    ]
  }
}