{
  "filename": "l\u2019elf_noir_du_mal_36px.png",
  "status": "success",
  "description": {
    "detailed_description": "Lielf Noir DV is a contemporary sans-serif typeface that blends a geometric foundation with subtle humanist details. Its construction is characterized by clean, precise lines and a consistent stroke weight, creating a sense of order and clarity. The letterforms are generally open and airy, with generous counters and a high x-height, contributing to excellent legibility even at small sizes. However, the font avoids a purely geometric rigidity through the introduction of subtle curves in the terminals and the slight variation in stroke weight within individual characters. This subtle humanization adds a touch of warmth and approachability to the otherwise stark geometric structure. The overall effect is a typeface that feels both modern and timeless, capable of conveying a sense of sophistication and professionalism without sacrificing readability. Lielf Noir DV is well-suited for a wide range of applications, from branding and editorial design to digital interfaces and signage. Its clean lines and strong legibility make it ideal for large-scale displays, while its subtle humanization prevents it from feeling overly cold or sterile. The font's contemporary aesthetic and versatility make it a strong choice for projects that require a balance of clarity, sophistication, and approachability.",
    "technical_characteristics": [
      "Geometric construction",
      "Consistent stroke weight",
      "High x-height",
      "Open counters",
      "Subtly rounded terminals",
      "Slight variation in stroke weight"
    ],
    "personality_traits": [
      "Confidently geometric",
      "Subtly humanist",
      "Clean and precise",
      "Modern and timeless",
      "Sophisticated and professional",
      "Approachable and readable",
      "Versatile and adaptable"
    ],
    "practical_contexts": [
      "Branding and identity design",
      "Editorial design and typography",
      "Digital interfaces and web design",
      "Signage and wayfinding",
      "Large-scale displays and presentations"
    ],
    "cultural_intuition": [
      "Evokes a sense of modernism and clarity",
      "Suggests a balance of sophistication and approachability",
      "Reflects a contemporary design aesthetic",
      "Connects to a sense of order and structure",
      "Communicates a sense of professionalism and authority"
    ],
    "search_keywords": [
      "Geometric sans-serif",
      "Contemporary typeface",
      "High x-height",
      "Open counters",
      "Rounded terminals",
      "Clean and precise",
      "Modern and timeless",
      "Sophisticated and professional",
      "Approachable and readable",
      "Versatile and adaptable",
      "Branding",
      "Editorial design",
      "Digital interfaces",
      "Signage",
      "Large-scale displays",
      "Modernism",
      "Clarity",
      "Professionalism",
      "Authority"
    ]
  }
}